apispec_clear_unusable-1.0.1.dist-info/METADATA
apispec_clear_unusable-1.0.1.dist-info/RECORD
apispec_clear_unusable-1.0.1.dist-info/WHEEL
apispec_clear_unusable-1.0.1.dist-info/top_level.txt
brunoais/apispec/ext/clear_unusable.py
