Metadata-Version: 2.1
Name: apispec-clear-unusable
Version: 1.0.1
Summary: Plugin for apispec which helps reusing the documentation on a muti-endpoint function/method.
Home-page: https://github.com/brunoais/apispec-clear-unusable
Author: Brunoais
Author-email: brunoaiss@gmail.com
License: MIT
Platform: UNKNOWN
Classifier: Programming Language :: Python :: 3
Classifier: Programming Language :: Python :: 3.6
Classifier: License :: OSI Approved :: MIT License
Classifier: Operating System :: OS Independent
Requires-Dist: apispec
